{
  "ingredients": [
    "1 cup Basmati rice",
    "1 cup water",
    "1/2 tbsp olive oil",
    "chopped green onions (optional)",
    "parsely (optional)",
    "Instant Pot"
  ],
  "notes": [],
  "rating": 1,
  "recipe": [
    "Rinse the Basmati rice with cold water. Add rice, water, and oil to instant pot. Cook for 8 minutes on high pressure, then allow 5 minutes for natural pressure release",
    "Toss with the green onions and parsely"
  ],
  "source": "https://mommyshomecooking.com/instant-pot-fluffy-rice/"
}
